addons/__init__.py
enciyo/__init__.py
enciyo/main.py
enciyo/utils.py
enciyo/addons/__init__.py
enciyo/addons/binding.py
enciyo/interceptor/__init__.py
enciyo/interceptor/cache.py
enciyo/interceptor/chain.py
enciyo/interceptor/filte.py
enciyo/interceptor/interceptor.py
enciyo/interceptor/markdown.py
enciyo/interceptor/vote.py
enciyo/model/__init__.py
enciyo/model/conversation.py
enciyo/model/request.py
gh_copilot_history-0.1.0.dist-info/LICENCE
gh_copilot_history-0.1.0.dist-info/METADATA
gh_copilot_history-0.1.0.dist-info/WHEEL
gh_copilot_history-0.1.0.dist-info/top_level.txt
gh_copilot_history-0.1.0.dist-info/RECORD
